Metadata-Version: 1.0
Name: distributions-pak
Version: 0.1
Summary: Gaussian distributions
Home-page: UNKNOWN
Author: Yangfan
Author-email: xyf3333@gmail.com
License: UNKNOWN
Platform: UNKNOWN
